{
  "gender": {
    "Description": "sex of the participant",
    "Levels": {
      "M": "biological male",
      "F": "biological female"
    },
    "Annotations": {
      "IsAbout": {
        "TermURL": "nb:Sex",
        "Label": "Sex"
      },
      "VariableType": "Categorical",
      "Levels": {
        "F": {
          "TermURL": "snomed:248152002",
          "Label": "Female"
        },
        "M": {
          "TermURL": "snomed:248153007",
          "Label": "Male"
        }
      },
      "MissingValues": []
    }
  },
  "participant_id": {
    "LongName": "participant identifier",
    "Description": "unique participant label",
    "Annotations": {
      "IsAbout": {
        "TermURL": "nb:ParticipantID",
        "Label": "Participant ID"
      },
      "VariableType": "Identifier"
    }
  },
  "age": {
    "Description": "age of the participant",
    "Units": "years",
    "Annotations": {
      "IsAbout": {
        "TermURL": "nb:Age",
        "Label": "Age"
      },
      "VariableType": "Continuous",
      "Format": {
        "TermURL": "nb:FromFloat",
        "Label": "float"
      },
      "MissingValues": [
        "n/a",
        "N/A",
        "na",
        "NA",
        "nan",
        "NaN",
        ""
      ]
    }
  },
  "handedness": {
    "Description": "dominant hand of the participant",
    "Levels": {
      "right_handed": "righty",
      "left_handed": "lefty"
    }
  },
  "major": {
    "Description": "undergraduate participant",
    "Levels": {
      "nursing": "undergraduate student majoring in nursing",
      "medicine": "undergraduate student majoring in medicine",
      "industrial_engineering": "undergraduate student majoring in industrial engineering",
      "industrial_automation": "undergraduate student majoring in industrial automation"
    }
  }
}