{
    "Age": {
        "Annotations": {
            "IsAbout": {
                "TermURL": "nb:Age",
                "Label": ""
            },
            "Transformation": {
                "TermURL": "nb:FromInt",
                "Label": "integer data"
            },
            "MissingValues": [
                "",
                "n/a",
                " "
            ]
        },
        "Description": "There should have been a description here, but there wasn't. :("
    },
    "Gender": {
        "Annotations": {
            "IsAbout": {
                "TermURL": "nb:Sex",
                "Label": ""
            },
            "Levels": {
                "F": {
                    "TermURL": "snomed:248152002",
                    "Label": ""
                },
                "M": {
                    "TermURL": "snomed:248153007",
                    "Label": ""
                }
            }
        },
        "Description": "There should have been a description here, but there wasn't. :("
    },
    "MMSE": {
        "Annotations": {
            "IsAbout": {
                "TermURL": "nb:Assessment",
                "Label": ""
            },
            "IsPartOf": {
                "TermURL": "snomed:414750000",
                "Label": ""
            }
        },
        "Description": "There should have been a description here, but there wasn't. :("
    },
    "STROOP color": {
        "Description": "There should have been a description here, but there wasn't. :("
    },
    "STROOP interference": {
        "Description": "There should have been a description here, but there wasn't. :("
    },
    "STROOP reading": {
        "Description": "There should have been a description here, but there wasn't. :("
    },
    "WAIS-III digits test": {
        "Annotations": {
            "IsAbout": {
                "TermURL": "nb:Assessment",
                "Label": ""
            },
            "IsPartOf": {
                "TermURL": "snomed:273917002",
                "Label": ""
            }
        },
        "Description": "There should have been a description here, but there wasn't. :("
    },
    "WMS-III logical memory I": {
        "Annotations": {
            "IsAbout": {
                "TermURL": "nb:Assessment",
                "Label": ""
            },
            "IsPartOf": {
                "TermURL": "snomed:273921009",
                "Label": ""
            }
        },
        "Description": "There should have been a description here, but there wasn't. :("
    },
    "WSM-III logical memory II": {
        "Annotations": {
            "IsAbout": {
                "TermURL": "nb:Assessment",
                "Label": ""
            },
            "IsPartOf": {
                "TermURL": "snomed:273921009",
                "Label": ""
            }
        },
        "Description": "There should have been a description here, but there wasn't. :("
    },
    "participant_id": {
        "Annotations": {
            "IsAbout": {
                "TermURL": "nb:ParticipantID",
                "Label": ""
            },
            "Identifies": "participant"
        },
        "Description": "There should have been a description here, but there wasn't. :("
    }
}